pymodia/__init__.py
pymodia/_version.py
pymodia/allowed_settings.txt
pymodia/atom_data.json
pymodia/data.py
pymodia/fragment.py
pymodia/helpers.py
pymodia/modiagram.py
pymodia/molecule.py
pymodia/settings.py
pymodia-0.5.3.dist-info/licenses/LICENSE
pymodia-0.5.3.dist-info/METADATA
pymodia-0.5.3.dist-info/WHEEL
pymodia-0.5.3.dist-info/top_level.txt
pymodia-0.5.3.dist-info/RECORD
