Metadata-Version: 2.4
Name: pymodia
Version: 0.5.3
Summary: A Python package for constructing clear, educational molecular orbital diagrams from qualitative models or minimal-basis electronic structure calculations.
Author-email: Ivo Filot <ivo@ivofilot.nl>, Joeri van Limpt <joerivanlimpt@live.nl>
Maintainer-email: Ivo Filot <ivo@ivofilot.nl>
License: GPL-3.0-or-later
Project-URL: Homepage, https://github.com/ifilot/pymodia
Project-URL: Documentation, https://ifilot.github.io/pymodia/
Project-URL: Source, https://github.com/ifilot/pymodia
Project-URL: Issues, https://github.com/ifilot/pymodia/issues
Keywords: chemistry,molecular orbitals,quantum chemistry,visualization,education
Classifier: Programming Language :: Python :: 3
Classifier: Operating System :: OS Independent
Requires-Python: >=3.9
License-File: LICENSE
Requires-Dist: matplotlib
Requires-Dist: numpy
Requires-Dist: drawsvg
Requires-Dist: cairosvg
Dynamic: license-file
